setup.py
la_metro/__init__.py
python_lametro_api.egg-info/PKG-INFO
python_lametro_api.egg-info/SOURCES.txt
python_lametro_api.egg-info/dependency_links.txt
python_lametro_api.egg-info/top_level.txt